setup.py
TracCtxtnavAdd.egg-info/PKG-INFO
TracCtxtnavAdd.egg-info/SOURCES.txt
TracCtxtnavAdd.egg-info/entry_points.txt
TracCtxtnavAdd.egg-info/top_level.txt
ctxtnavadd/__init__.py
ctxtnavadd/api.py
ctxtnavadd/web_ui.py
ctxtnavadd/htdocs/js/ctxtnavadd.js
ctxtnavadd/templates/ctxtnavadd.cs
