Metadata-Version: 1.0
Name: TracCtxtnavAdd
Version: 1.1-r1
Summary: Allow adding to the ctxtnav bar of other plugins.
Home-page: http://trac-hacks.org/wiki/CtxtnavAddPlugin
Author: Noah Kantrowitz
Author-email: coderanger@yahoo.com
License: BSD
Keywords: trac plugin ctxtnav
Platform: UNKNOWN
